circtools/__init__.py
circtools/circtools.py
circtools/circ_module/__init__.py
circtools/circ_module/circ_template.py
circtools/circtest/__init__.py
circtools/circtest/circtest.py
circtools/conservation/FetchOrthologs.py
circtools/conservation/FetchRegionGeneSequence.py
circtools/conservation/LiftOver.py
circtools/conservation/SequenceAlignment.py
circtools/conservation/__init__.py
circtools/conservation/conservation.py
circtools/conservation/liftOver
circtools/conservation/config/example.config
circtools/contrib/circtest/.Rbuildignore
circtools/contrib/circtest/.gitignore
circtools/contrib/circtest/DESCRIPTION
circtools/contrib/circtest/NAMESPACE
circtools/contrib/circtest/README.md
circtools/contrib/circtest/R/Circ.filter.R
circtools/contrib/circtest/R/Circ.linePlot.R
circtools/contrib/circtest/R/Circ.ratioplot.R
circtools/contrib/circtest/R/Circ.test.R
circtools/contrib/circtest/R/HostGeneCount.R
circtools/contrib/circtest/R/documentData.R
circtools/contrib/circtest/R/summarySE.R
circtools/contrib/circtest/data/Circ.rda
circtools/contrib/circtest/data/Coordinates.rda
circtools/contrib/circtest/data/Linear.rda
circtools/contrib/circtest/man/Circ.Rd
circtools/contrib/circtest/man/Circ.filter.Rd
circtools/contrib/circtest/man/Circ.lineplot.Rd
circtools/contrib/circtest/man/Circ.ratioplot.Rd
circtools/contrib/circtest/man/Circ.test.Rd
circtools/contrib/circtest/man/Coordinates.Rd
circtools/contrib/circtest/man/HostGeneCount.Rd
circtools/contrib/circtest/man/Linear.Rd
circtools/contrib/circtest/man/read_one_scanBam.Rd
circtools/contrib/circtest/man/read_scanBam.Rd
circtools/contrib/circtest/man/summarySE.Rd
circtools/contrib/liftOver/AMD64/linux/liftOver
circtools/contrib/liftOver/AMD64/mac/liftOver
circtools/contrib/liftOver/ARM64/mac/liftOver
circtools/contrib/mafft/AMD64/linux/mafft.bat
circtools/contrib/mafft/AMD64/linux/mafftdir/bin/mafft
circtools/contrib/mafft/AMD64/linux/mafftdir/libexec/addsingle
circtools-2.0.3.dist-info/LICENSE
circtools-2.0.3.dist-info/METADATA
circtools-2.0.3.dist-info/WHEEL
circtools-2.0.3.dist-info/entry_points.txt
circtools-2.0.3.dist-info/top_level.txt
circtools-2.0.3.dist-info/RECORD
