Metadata-Version: 2.1
Name: circtools
Version: 2.0.3
Summary: circtools - a circular RNA toolbox
Home-page: https://github.com/jakobilab/circtools
Author: Tobias Jakobi
Author-email: tjakobi@arizona.edu
License: GNU General Public License (GPL)
Project-URL: Bug Reports, https://github.com/jakobilab/circtools/issues
Project-URL: Jakobi Lab, https://jakobilab.org
Project-URL: Source, https://github.com/jakobilab/circtools
Project-URL: Documentation, https://docs.circ.tools
Keywords: circRNA,circular RNA bioinformatics
Classifier: Development Status :: 4 - Beta
Classifier: Intended Audience :: Science/Research
Classifier: Topic :: Scientific/Engineering :: Bio-Informatics
Classifier: Programming Language :: Python :: 3.8
Classifier: Programming Language :: Python :: 3.9
Classifier: Programming Language :: Python :: 3.10
Classifier: Programming Language :: Python :: 3.11
Classifier: Programming Language :: Python :: 3.12
Classifier: Programming Language :: Python :: 3.13
Requires-Python: >=3.8
License-File: LICENSE
Requires-Dist: Cython
Requires-Dist: HTSeq>=2.0.0
Requires-Dist: PyYAML>=6.0.2
Requires-Dist: biopython>=1.71
Requires-Dist: certifi
Requires-Dist: matplotlib>=3.0
Requires-Dist: nanofilt
Requires-Dist: numdifftools
Requires-Dist: numpy<2.0.0,>=1.14.5
Requires-Dist: openpyxl
Requires-Dist: pandas>=0.25.0
Requires-Dist: pathos>=0.3.0
Requires-Dist: primer3-py>=2.2.0
Requires-Dist: pybedtools>=0.7.10
Requires-Dist: pysam>=0.16.0.1
Requires-Dist: reportlab>=3.3.0
Requires-Dist: requests>=2.32.3
Requires-Dist: scipy>=0.19.0
Requires-Dist: seaborn
Requires-Dist: statsmodels
Requires-Dist: tqdm>=4.67.1
